main.py
mcp_akshare-0.0.2.dist-info/METADATA
mcp_akshare-0.0.2.dist-info/WHEEL
mcp_akshare-0.0.2.dist-info/entry_points.txt
mcp_akshare-0.0.2.dist-info/top_level.txt
mcp_akshare-0.0.2.dist-info/RECORD
