Metadata-Version: 2.4
Name: mcp-akshare
Version: 0.0.2
Summary: Add your description here
Requires-Python: >=3.13
Requires-Dist: akshare>=1.16.76
Requires-Dist: fastmcp>=2.0.0
